arcade_ytx/__init__.py
arcade_ytx/main.py
arcade_ytx/game_01/__init__.py
arcade_ytx/game_01/rock_paper_scissors.py
arcade_ytx/game_02/__init__.py
arcade_ytx/game_02/guess_number.py
arcade_ytx/game_03/__init__.py
arcade_ytx/game_03/tic_tac_toe.py
arcade_ytx/game_04/__init__.py
arcade_ytx/game_04/bank_account.py
arcade_ytx/game_04/main.py
arcade_ytx-1.2.dist-info/licenses/LICENSE
arcade_ytx-1.2.dist-info/METADATA
arcade_ytx-1.2.dist-info/WHEEL
arcade_ytx-1.2.dist-info/entry_points.txt
arcade_ytx-1.2.dist-info/top_level.txt
arcade_ytx-1.2.dist-info/RECORD
